edger/__init__.py
edger/config.ini
edger/config.py
edger/config_gui.py
edger/edger.py
edger/jiggler.py
edger/log.py
edger/utils.py
edger/data/edger.ico
edger-0.1.3.dist-info/LICENSE
edger-0.1.3.dist-info/METADATA
edger-0.1.3.dist-info/WHEEL
edger-0.1.3.dist-info/entry_points.txt
edger-0.1.3.dist-info/top_level.txt
edger-0.1.3.dist-info/RECORD
