Metadata-Version: 2.2
Name: edger
Version: 0.1.3
Summary: Redirect Microsoft Edge to your preferred browser
Home-page: https://github.com/phwelo/edger
Author: Daniel Agans
Author-email: Daniel Agans <phwelo@qwe.rip>
License: MIT License
Project-URL: Homepage, https://github.com/phwelo/edger
Project-URL: Issues, https://github.com/phwelo/edger/issues
Classifier: Development Status :: 4 - Beta
Classifier: Environment :: Win32 (MS Windows)
Classifier: Intended Audience :: End Users/Desktop
Classifier: License :: OSI Approved :: MIT License
Classifier: Programming Language :: Python :: 3
Classifier: Topic :: Utilities
Requires-Python: >=3.6
License-File: LICENSE
Requires-Dist: pystray>=0.17.0
Requires-Dist: Pillow>=8.0.0
Requires-Dist: pywin32>=300
Requires-Dist: psutil>=5.9.0
Requires-Dist: pyautogui>=0.9.53
Requires-Dist: pyperclip>=1.8.2
Requires-Dist: configparser>=5.2.0
Dynamic: author
Dynamic: home-page
Dynamic: requires-python
